odoo/addons/purchase_invoice_plan/README.rst
odoo/addons/purchase_invoice_plan/__init__.py
odoo/addons/purchase_invoice_plan/__manifest__.py
odoo/addons/purchase_invoice_plan/data/purchase_data.xml
odoo/addons/purchase_invoice_plan/i18n/es.po
odoo/addons/purchase_invoice_plan/i18n/it.po
odoo/addons/purchase_invoice_plan/i18n/pt_BR.po
odoo/addons/purchase_invoice_plan/i18n/purchase_invoice_plan.pot
odoo/addons/purchase_invoice_plan/models/__init__.py
odoo/addons/purchase_invoice_plan/models/purchase_invoice_plan.py
odoo/addons/purchase_invoice_plan/models/purchase_order.py
odoo/addons/purchase_invoice_plan/readme/CONTRIBUTORS.md
odoo/addons/purchase_invoice_plan/readme/DESCRIPTION.md
odoo/addons/purchase_invoice_plan/readme/USAGE.md
odoo/addons/purchase_invoice_plan/security/ir.model.access.csv
odoo/addons/purchase_invoice_plan/static/description/icon.png
odoo/addons/purchase_invoice_plan/static/description/index.html
odoo/addons/purchase_invoice_plan/tests/__init__.py
odoo/addons/purchase_invoice_plan/tests/test_purchase_invoice_plan.py
odoo/addons/purchase_invoice_plan/views/purchase_view.xml
odoo/addons/purchase_invoice_plan/wizard/__init__.py
odoo/addons/purchase_invoice_plan/wizard/purchase_create_invoice_plan.py
odoo/addons/purchase_invoice_plan/wizard/purchase_create_invoice_plan_view.xml
odoo/addons/purchase_invoice_plan/wizard/purchase_make_planned_invoice.py
odoo/addons/purchase_invoice_plan/wizard/purchase_make_planned_invoice_view.xml
odoo_addon_purchase_invoice_plan-18.0.1.0.2.dist-info/METADATA
odoo_addon_purchase_invoice_plan-18.0.1.0.2.dist-info/WHEEL
odoo_addon_purchase_invoice_plan-18.0.1.0.2.dist-info/top_level.txt
odoo_addon_purchase_invoice_plan-18.0.1.0.2.dist-info/RECORD
