Metadata-Version: 2.1
Name: odoo-addon-purchase_invoice_plan
Version: 18.0.1.0.2
Requires-Python: >=3.10
Requires-Dist: odoo-addon-purchase_open_qty==18.0.*
Requires-Dist: odoo==18.0.*
Summary: Add to purchases order, ability to manage future invoice plan
Home-page: https://github.com/OCA/purchase-workflow
License: AGPL-3
Author: Ecosoft,Odoo Community Association (OCA)
Author-email: support@odoo-community.org
Classifier: Programming Language :: Python
Classifier: Framework :: Odoo
Classifier: Framework :: Odoo :: 18.0
Classifier: License :: OSI Approved :: GNU Affero General Public License v3
Classifier: Development Status :: 3 - Alpha
